winterboot/Autowired.py
winterboot/DTO.py
winterboot/MockedService.py
winterboot/Service.py
winterboot/Stubs.py
winterboot/TestData.py
winterboot/TestDataForStub.py
winterboot/WinterBoot.py
winterboot/__init__.py
winterboot-0.7.dist-info/METADATA
winterboot-0.7.dist-info/WHEEL
winterboot-0.7.dist-info/top_level.txt
winterboot-0.7.dist-info/RECORD
