Metadata-Version: 2.1
Name: winterboot
Version: 0.7
Summary: Winterboot is not SpringBoot
Home-page: https://github.com/kode-konveyor/winterboot
Author: Arpad Magosanyi
Author-email: mag@kodekonveyor.com
License: UNKNOWN
Platform: UNKNOWN
Classifier: Programming Language :: Python :: 3
Classifier: License :: OSI Approved :: GNU General Public License v3 or later (GPLv3+)
Classifier: Operating System :: OS Independent
